setup.py
ppmc/__init__.py
ppmc.egg-info/PKG-INFO
ppmc.egg-info/SOURCES.txt
ppmc.egg-info/dependency_links.txt
ppmc.egg-info/requires.txt
ppmc.egg-info/top_level.txt
ppmc.egg-info/zip-safe