Metadata-Version: 1.0
Name: ppmc
Version: 0.1.5
Summary: Calculate Pearson Product Moment Correlation between two (or more) vectors.
Home-page: http://nick.seidenman.net/pystuff/
Author: Nick Seidenman
Author-email: seidenman@wehi.edu.au
License: UNKNOWN
Keywords: pearson statistics correlation
Platform: UNKNOWN
